quickstruct/__init__.py
quickstruct/common.py
quickstruct/error.py
quickstruct/field.py
quickstruct/quickstruct.py
quickstruct/struct_builder.py
quickstruct/utils.py
quickstruct-0.2.1.dist-info/METADATA
quickstruct-0.2.1.dist-info/WHEEL
quickstruct-0.2.1.dist-info/LICENSE
quickstruct-0.2.1.dist-info/RECORD
