Metadata-Version: 2.1
Name: quickstruct
Version: 0.2.1
Summary: A small library to ease the creation, usage, serialization and deserialization of C structs.
Home-page: https://github.com/xpodev/quickstruct
License: MIT
Author: Binyamin Y Cohen
Author-email: binyamincohen555@gmail.com
Requires-Python: >=3.8,<4.0
Classifier: License :: OSI Approved :: MIT License
Classifier: Programming Language :: Python :: 3
Classifier: Programming Language :: Python :: 3.8
Classifier: Programming Language :: Python :: 3.9
Classifier: Programming Language :: Python :: 3.10
Classifier: Programming Language :: Python :: 3.11
Project-URL: Repository, https://github.com/xpodev/quickstruct
